[
    {
        "id": 1,
        "brand": "CIF",
        "name": "CIF CREMA ORIGINAL FRASCO 375G",
        "price": 7.0,
        "image": "/assets/img-products/CIF CREMA ORIGINAL FRASCO 375G.jpg",
        "quantity": 2
    },

    {
        "id": 2,
        "brand": "CIELO",
        "name": "Agua Cielo sin gas 2.5 lt",
        "price": 3.0,
        "image": "/assets/img-products/agua2.5-cielo.jpg",
        "quantity": 3
    },

    {
        "id": 3,
        "brand": "CIELO",
        "name": "Agua Cielo con Chupon 1 lt",
        "price": 2.4,
        "image": "/assets/img-products/aguachupon-cielo.jpg",
        "quantity": 7
    },

    {
        "id": 4,
        "brand": "CIELO",
        "name": "Agua Cielo Caja 20 lt",
        "price": 24.8,
        "image": "/assets/img-products/aguacaja-cielo.jpg",
        "quantity": 1
    },

    {
        "id": 5,
        "brand": "CIELO",
        "name": "Agua Cielo Bidón 7 lt",
        "price": 7.9,
        "image": "/assets/img-products/aguabidon-cielo.jpg",
        "quantity": 4
    },

    {
        "id": 6,
        "brand": "CIELO",
        "name": "Agua Cielo Alcalina 625 ml",
        "price": 1.9,
        "image": "/assets/img-products/aguaalcalina-cielo.jpg",
        "quantity": 4
    }
]
  